funcnodes_images/__init__.py
funcnodes_images/_numpy.py
funcnodes_images/_pillow.py
funcnodes_images/image_nodes.py
funcnodes_images/imagecontainer.py
funcnodes_images/utils.py
funcnodes_images-0.2.6.dist-info/licenses/LICENSE
funcnodes_images-0.2.6.dist-info/METADATA
funcnodes_images-0.2.6.dist-info/WHEEL
funcnodes_images-0.2.6.dist-info/entry_points.txt
funcnodes_images-0.2.6.dist-info/top_level.txt
funcnodes_images-0.2.6.dist-info/RECORD
