Metadata-Version: 2.4
Name: funcnodes-images
Version: 0.2.6
Summary: Basic functionalities to work with images in Funcnodes
Author-email: Julian Kimmig <julian.kimmig@linkdlab.de>
License: AGPL-3.0
Project-URL: homepage, https://github.com/Linkdlab/funcnodes_images
Project-URL: source, https://github.com/Linkdlab/funcnodes_images
Project-URL: tracker, https://github.com/Linkdlab/funcnodes_images/issues
Project-URL: download, https://pypi.org/project/funcnodes-images/#files
Classifier: Development Status :: 4 - Beta
Classifier: Intended Audience :: Developers
Classifier: Intended Audience :: Education
Classifier: Intended Audience :: Science/Research
Classifier: License :: OSI Approved :: GNU Affero General Public License v3 or later (AGPLv3+)
Requires-Python: >=3.11
License-File: LICENSE
Requires-Dist: funcnodes>=0.5.36
Requires-Dist: numpy
Requires-Dist: pillow
Requires-Dist: funcnodes-numpy
Dynamic: license-file
